tswift.py
tswift-0.7.0.dist-info/LICENSE.md
tswift-0.7.0.dist-info/METADATA
tswift-0.7.0.dist-info/WHEEL
tswift-0.7.0.dist-info/entry_points.txt
tswift-0.7.0.dist-info/top_level.txt
tswift-0.7.0.dist-info/RECORD
