Metadata-Version: 1.1
Name: tswift
Version: 0.7.0
Summary: MetroLyrics API
Home-page: https://github.com/brenns10/tswift
Author: Stephen Brennan
Author-email: stephen@brennan.io
License: Revised BSD
Keywords: lyrics metrolyrics scrape
Platform: UNKNOWN
Classifier: Programming Language :: Python :: 2
Classifier: Programming Language :: Python :: 3
Classifier: License :: OSI Approved :: BSD License
Classifier: Development Status :: 4 - Beta
Classifier: Topic :: Multimedia :: Sound/Audio
Classifier: Natural Language :: English
